MusicXMLSynthesizer/Synthesizer.py
MusicXMLSynthesizer/__init__.py
MusicXMLSynthesizer/to_xml.py
MusicXMLSynthesizer/utils.py
musicXML_synthesizer-0.9.14.dist-info/LICENSE
musicXML_synthesizer-0.9.14.dist-info/METADATA
musicXML_synthesizer-0.9.14.dist-info/WHEEL
musicXML_synthesizer-0.9.14.dist-info/top_level.txt
musicXML_synthesizer-0.9.14.dist-info/RECORD
