Metadata-Version: 2.1
Name: musicXML-synthesizer
Version: 0.9.14
Summary: A package to transform solola output to standard musicXML format
Home-page: https://github.com/SoloLa-Platform/MusicXML-Synthesizer
Author: ykhorizon
Author-email: ykhorizon@gmail.com
License: UNKNOWN
Platform: UNKNOWN
Classifier: Programming Language :: Python :: 3
Classifier: License :: OSI Approved :: MIT License
Classifier: Operating System :: OS Independent
Requires-Python: >=3.0
Requires-Dist: lxml
Requires-Dist: numpy
Requires-Dist: pretty-midi
